LICENSE.md
README.md
setup.cfg
setup.py
tidypath/__init__.py
tidypath/_helper.py
tidypath/config.py
tidypath/decorators.py
tidypath/fmt.py
tidypath/inspection.py
tidypath/paths.py
tidypath/storage.py
tidypath.egg-info/PKG-INFO
tidypath.egg-info/SOURCES.txt
tidypath.egg-info/dependency_links.txt
tidypath.egg-info/requires.txt
tidypath.egg-info/top_level.txt