Metadata-Version: 2.1
Name: tidypath
Version: 1.5.3
Summary: Automatically store/load data in a tidy, efficient way.
Home-page: https://github.com/medinajorge/tidypath
Download-URL: https://github.com/medinajorge/tidypath/archive/refs/tags/v1.4.5.tar.gz
Author: Jorge Medina Hernández
Author-email: medinahdezjorge@gmail.com
Keywords: tidy,project organization,project,organization,path,storage
Classifier: Programming Language :: Python :: 3
Classifier: Development Status :: 5 - Production/Stable
Classifier: License :: OSI Approved :: GNU Affero General Public License v3
Classifier: Operating System :: OS Independent
Classifier: Topic :: Scientific/Engineering
Classifier: Topic :: Office/Business
Classifier: Intended Audience :: Science/Research
Requires-Python: >=3
Provides-Extra: matplotlib
Provides-Extra: plotly
License-File: LICENSE.md
